hl/__init__.py
hl/_lib.py
hl/account.py
hl/api.py
hl/cloid.py
hl/constants.py
hl/errors.py
hl/exchange.py
hl/info.py
hl/network.py
hl/py.typed
hl/result.py
hl/signer.py
hl/subscriptions.py
hl/transport.py
hl/types.py
hl/universe.py
hl/validator.py
hl/ws.py
hl/ws_transport.py
hl_sdk-0.1.0.dist-info/WHEEL
hl_sdk-0.1.0.dist-info/METADATA
hl_sdk-0.1.0.dist-info/RECORD
