Metadata-Version: 2.4
Name: hl-sdk
Version: 0.1.0
Summary: An unofficial client SDK for Hyperliquid
Author: papicap
Author-email: papicap <212585295+papicap@users.noreply.github.com>
License-Expression: MIT
Classifier: Operating System :: OS Independent
Classifier: Typing :: Typed
Classifier: Intended Audience :: Developers
Classifier: License :: OSI Approved :: MIT License
Classifier: Programming Language :: Python :: 3
Classifier: Programming Language :: Python :: 3 :: Only
Classifier: Programming Language :: Python :: 3.11
Classifier: Programming Language :: Python :: 3.12
Classifier: Programming Language :: Python :: 3.13
Requires-Dist: eth-account>=0.13.7
Requires-Dist: eth-utils>=5.2.0
Requires-Dist: hexbytes>=1.3.0
Requires-Dist: httpx[http2]>=0.28.1
Requires-Dist: msgpack>=1.1.1
Requires-Dist: websockets>=15.0.1
Requires-Python: >=3.11
Project-URL: Documentation, https://papicapital.github.com/hl-sdk
Project-URL: Homepage, https://papicapital.github.com/hl-sdk
Project-URL: Repository, https://github.com/papicapital/hl-sdk/
